nmqn/__init__.py
nmqn/_common/__init__.py
nmqn/_common/config.py
nmqn/_common/path.py
nmqn/compare/__init__.py
nmqn/compare/_view.py
nmqn/compare/templetes/report.tpl.md
nmqn/compare/templetes/top.tpl.md
nmqn/crawl/__init__.py
nmqn/crawl/_crawler.py
nmqn/lib/__init__.py
nmqn/lib/crawler.py
nmqn/main.py
nmqn-0.0.1.dist-info/entry_points.txt
nmqn-0.0.1.dist-info/WHEEL
nmqn-0.0.1.dist-info/METADATA
nmqn-0.0.1.dist-info/RECORD
