Metadata-Version: 2.1
Name: nmqn
Version: 0.0.1
Summary: 
Home-page: UNKNOWN
License: UNKNOWN
Author: takeshi
Author-email: sci.and.eng@gmail.com
Requires-Python: >=3.6,<4.0
Classifier: Programming Language :: Python :: 3
Classifier: Programming Language :: Python :: 3.6
Classifier: Programming Language :: Python :: 3.7
Requires-Dist: aiohttp (>=3.5,<4.0)
Requires-Dist: click (>=7.0,<8.0)
Requires-Dist: jinja2 (>=2.10,<3.0)
Requires-Dist: pweave (>=0.30.3,<0.31.0)
Requires-Dist: pyppeteer (>=0.0.25,<0.0.26)
Requires-Dist: pyyaml (>=3.13,<4.0)
Requires-Dist: requests (>=2.21,<3.0)
Requires-Dist: requests-html (>=0.9.0,<0.10.0)
Requires-Dist: retry (>=0.9.2,<0.10.0)
